lang_custom/__init__.py
lang_custom/en.json
lang_custom/lang_custom.py
lang_custom-1.1.6.dist-info/licenses/LICENSE
lang_custom-1.1.6.dist-info/METADATA
lang_custom-1.1.6.dist-info/WHEEL
lang_custom-1.1.6.dist-info/top_level.txt
lang_custom-1.1.6.dist-info/RECORD
