Metadata-Version: 2.4
Name: lang_custom
Version: 1.1.6
Summary: A simple language manager for Python projects.
Home-page: https://github.com/GauCandy/lang_custom
Author: Gấu Kẹo
Author-email: gaulolipop@gmail.com
Keywords: language,i18n,json,sqlite,async,translation,bot
Classifier: Programming Language :: Python :: 3
Classifier: License :: OSI Approved :: MIT License
Classifier: Operating System :: OS Independent
Requires-Python: >=3.7
License-File: LICENSE
Requires-Dist: aiosqlite>=0.17.0
Dynamic: author
Dynamic: author-email
Dynamic: classifier
Dynamic: description
Dynamic: description-content-type
Dynamic: home-page
Dynamic: keywords
Dynamic: license-file
Dynamic: requires-dist
Dynamic: requires-python
Dynamic: summary
